spacy_cleaner/__init__.py
spacy_cleaner/cleaners.py
spacy_cleaner/processing/__init__.py
spacy_cleaner/processing/evaluators.py
spacy_cleaner/processing/helpers.py
spacy_cleaner/processing/mutators.py
spacy_cleaner/processing/removers.py
spacy_cleaner/processing/replacers.py
spacy_cleaner/processing/transformers.py
spacy_cleaner-3.2.1.dist-info/LICENSE
spacy_cleaner-3.2.1.dist-info/METADATA
spacy_cleaner-3.2.1.dist-info/WHEEL
spacy_cleaner-3.2.1.dist-info/RECORD
