Metadata-Version: 2.1
Name: spacy-cleaner
Version: 3.2.1
Summary: Easily clean text with spaCy!
Home-page: https://github.com/Ce11an/spacy-cleaner
License: MIT
Author: spacy-cleaner
Author-email: hallcellan@gmail.com
Requires-Python: >=3.8,<3.12
Classifier: Development Status :: 5 - Production/Stable
Classifier: Intended Audience :: Developers
Classifier: License :: OSI Approved :: MIT License
Classifier: Operating System :: OS Independent
Classifier: Programming Language :: Python :: 3
Classifier: Programming Language :: Python :: 3.8
Classifier: Programming Language :: Python :: 3.9
Classifier: Programming Language :: Python :: 3.10
Classifier: Programming Language :: Python :: 3.11
Classifier: Topic :: Software Development :: Libraries :: Python Modules
Requires-Dist: spacy (>=3.7.2,<3.8.0)
Requires-Dist: spacy-lookups-data (>=1.0.5,<1.1.0)
Requires-Dist: tqdm (>=4.66.1,<4.67.0)
Requires-Dist: types-tqdm (>=4.66.0.5,<5.0.0.0)
Project-URL: Repository, https://github.com/Ce11an/spacy-cleaner
